{
  "breathing": {
    "name": "呼吸觉察",
    "duration": "1分钟",
    "guide_audio": "breathing/breathing_guide_female.mp3",
    "background_audio": "breathing/breathing_background.mp3",
    "output_audio": "breathing/breathing_complete.mp3",
    "background_volume": 0.25,
    "fade_in": 2,
    "fade_out": 3
  },
  "body-scan": {
    "name": "身体扫描",
    "duration": "3分钟",
    "guide_audio": "body-scan/body-scan_guide_female.mp3",
    "background_audio": "body-scan/body-scan_background.mp3",
    "output_audio": "body-scan/body-scan_complete.mp3",
    "background_volume": 0.2,
    "fade_in": 3,
    "fade_out": 4
  },
  "meditation": {
    "name": "正念冥想",
    "duration": "5分钟",
    "guide_audio": "meditation/meditation_guide_female.mp3",
    "background_audio": "meditation/meditation_background.mp3",
    "output_audio": "meditation/meditation_complete.mp3",
    "background_volume": 0.2,
    "fade_in": 4,
    "fade_out": 5
  },
  "relaxation": {
    "name": "深度放松",
    "duration": "7分钟",
    "guide_audio": "relaxation/relaxation_guide_female.mp3",
    "background_audio": "relaxation/relaxation_background.mp3",
    "output_audio": "relaxation/relaxation_complete.mp3",
    "background_volume": 0.15,
    "fade_in": 5,
    "fade_out": 6
  }
}